pavo_cristatus/__init__.py
pavo_cristatus/cli.py
pavo_cristatus/constants.py
pavo_cristatus/directory_walk_configuration.py
pavo_cristatus/pavo_cristatus_namespace.py
pavo_cristatus/python_file.py
pavo_cristatus/utilities.py
pavo_cristatus/compression/__init__.py
pavo_cristatus/dependency_injection/__init__.py
pavo_cristatus/dependency_injection/ploceidae_configurator.py
pavo_cristatus/interaction_sequence_generators/__init__.py
pavo_cristatus/interaction_sequence_generators/display_all_interaction_sequence_generator.py
pavo_cristatus/interaction_sequence_generators/rebuild_all_interaction_sequence_generator.py
pavo_cristatus/interaction_sequence_generators/utilities.py
pavo_cristatus/interactions/__init__.py
pavo_cristatus/interactions/pavo_cristatus_result.py
pavo_cristatus/interactions/pavo_cristatus_status.py
pavo_cristatus/interactions/annotated_project_loader_interaction/__init__.py
pavo_cristatus/interactions/annotated_project_loader_interaction/annotated_project_loader_interaction.py
pavo_cristatus/interactions/annotated_symbol_presenter_interaction/__init__.py
pavo_cristatus/interactions/annotated_symbol_presenter_interaction/annotated_symbol_presenter_interaction.py
pavo_cristatus/interactions/non_annotated_project_loader_interaction/__init__.py
pavo_cristatus/interactions/non_annotated_project_loader_interaction/non_annotated_project_loader_interaction.py
pavo_cristatus/interactions/pavo_cristatus_result_monad/__init__.py
pavo_cristatus/interactions/pavo_cristatus_result_monad/bindee_definition.py
pavo_cristatus/interactions/pavo_cristatus_result_monad/higher_order_bindee.py
pavo_cristatus/interactions/pavo_cristatus_result_monad/pavo_cristatus_null_result.py
pavo_cristatus/interactions/pavo_cristatus_result_monad/pavo_cristatus_result_monad.py
pavo_cristatus/interactions/repository_interaction/__init__.py
pavo_cristatus/interactions/repository_interaction/operations.py
pavo_cristatus/interactions/repository_interaction/repository_interaction.py
pavo_cristatus-0.5.7.0.dist-info/LICENSE
pavo_cristatus-0.5.7.0.dist-info/METADATA
pavo_cristatus-0.5.7.0.dist-info/WHEEL
pavo_cristatus-0.5.7.0.dist-info/entry_points.txt
pavo_cristatus-0.5.7.0.dist-info/top_level.txt
pavo_cristatus-0.5.7.0.dist-info/RECORD
