Metadata-Version: 2.1
Name: pavo-cristatus
Version: 0.5.7.0
Summary: type hints ide plugin
Home-page: https://github.com/MATTHEWFRAZER/pavo_cristatus
Author: Matthew Frazer
Author-email: mfrazeriguess@gmail.com
License: MIT
Keywords: ide plugin
Platform: UNKNOWN
Classifier: Programming Language :: Python :: 3.5
Classifier: Programming Language :: Python :: 3.6
Classifier: Programming Language :: Python :: 3.7
License-File: LICENSE
Requires-Dist: PyMonad (==1.3)
Requires-Dist: decorator (==4.4.2)
Requires-Dist: more-itertools (==8.7.0)
Requires-Dist: picidae (==1.0.6)
Requires-Dist: ploceidae (==2.0.34)
Requires-Dist: python-sql (==1.1.0)
Requires-Dist: trochilidae (==2.1.10)
